monitor/DialogStatusOperator.py
monitor/Status.py
monitor/StatusCenter.py
monitor/StatusOperator.py
monitor/__init__.py
monitor/dialog/HitDialogManager.py
monitor/dialog/LoadingHitDialog.py
monitor/dialog/__init__.py
EasyMonitor-0.0.3.dist-info/LICENSE
EasyMonitor-0.0.3.dist-info/METADATA
EasyMonitor-0.0.3.dist-info/WHEEL
EasyMonitor-0.0.3.dist-info/top_level.txt
EasyMonitor-0.0.3.dist-info/RECORD
